{"blogs_fixissue_html2canvas.md":"CXnAgr2n","blogs_git_pr.md":"BNdmkx8A","blogs_git_standard.md":"CLFFwi7o","blogs_git_work.md":"DSq2pfK1","blogs_interview_builded.md":"Bfq_-R8L","blogs_interview_cicd.md":"T5WpavvO","blogs_interview_examination_questions.md":"B0BpNfu3","blogs_interview_http.md":"a7Lj6rCI","blogs_interview_index.md":"CSIBRfvD","blogs_interview_javascript.md":"Ci01pKLr","blogs_interview_js_extend.md":"RhuL9ine","blogs_interview_miniprogram_lifecycle.md":"MOzKDP9h","blogs_interview_miniprogram_mini.md":"BjA5wNtV","blogs_interview_miniprogram_navigate.md":"CbZS-S01","blogs_interview_miniprogram_optimization.md":"C46NoLSJ","blogs_interview_miniprogram_webview_jscore.md":"DFdYNteF","blogs_interview_module.md":"BWhACgBs","blogs_interview_node_buffer.md":"SYvJkVoG","blogs_interview_node_nodejs.md":"gLQ1hQgc","blogs_interview_node_pagination.md":"DLq-_1Bs","blogs_interview_other.md":"CCnXYv8q","blogs_interview_vue2_404.md":"D3sMntCs","blogs_interview_vue2_bind.md":"cbI2uh94","blogs_interview_vue2_communication.md":"Doh71HFx","blogs_interview_vue2_components_plugin.md":"C6Y89OT6","blogs_interview_vue2_data.md":"CTIvQHeb","blogs_interview_vue2_data_object_add_attrs.md":"BOFzqQ5E","blogs_interview_vue2_directive.md":"BIfUWwin","blogs_interview_vue2_err.md":"CWyVqK7d","blogs_interview_vue2_filter.md":"DRKNfJGr","blogs_interview_vue2_first_page_time.md":"DwCdm0sL","blogs_interview_vue2_if_for.md":"Cp-bYP8T","blogs_interview_vue2_if_show.md":"Buc82i0_","blogs_interview_vue2_keepalive.md":"DfqxNDMX","blogs_interview_vue2_key.md":"CkI6Y0gY","blogs_interview_vue2_lifecycle.md":"BvwZh7Nz","blogs_interview_vue2_mixin.md":"D05Sg9i-","blogs_interview_vue2_modifier.md":"DLNKT4xB","blogs_interview_vue2_new_vue.md":"DBuBSmnn","blogs_interview_vue2_nexttick.md":"BJHOHvQ3","blogs_interview_vue2_observable.md":"D-y40b_3","blogs_interview_vue2_permission.md":"Co8VHgtv","blogs_interview_vue2_slot.md":"fxzfQ1iC","blogs_interview_vue2_spa.md":"C1m57RlI","blogs_interview_vue2_ssr.md":"DYK3O1U4","blogs_interview_vue2_vnode.md":"C9lVGb2h","blogs_interview_vue2_vue.md":"B7Lx3McU","blogs_interview_vue2_vue3_vue2.md":"y1Kv8hWJ","blogs_interview_vue3_performance.md":"9um3asfm","blogs_interview_vue3_proxy.md":"CY0Vw8GH","blogs_interview_vue3_treeshaking.md":"DiWMhcbw","blogs_interview_vuerouter.md":"DioPyF2S","blogs_interview_web_safe.md":"AVn5lslr","blogs_javascript_bigfileupload.md":"-_7bkbyY","blogs_javascript_chunktask.md":"D10sy5So","blogs_javascript_eventloop.md":"C2iNetTs","blogs_javascript_file.md":"D0HBG81G","blogs_javascript_normalutil.md":"EfTdNo7R","blogs_javascript_promise.md":"C8YTnDcS","blogs_javascript_unique.md":"BqixRL6a","blogs_node_nest.md":"BRteYO6y","blogs_node_nest_swagger.md":"BXqilv1o","blogs_node_nest_typeorm.md":"Bwfe4Wwh","blogs_node_node.md":"B4QBNtmf","blogs_node_pm2.md":"CumBH910","blogs_react_reacthooks_index.md":"D71wsCws","blogs_react_reacthooks_usecallback.md":"Hp5jhU1i","blogs_react_reacthooks_usecontext.md":"ijpUAyb0","blogs_react_reacthooks_useeffect.md":"CdnGUYHr","blogs_react_reacthooks_uselayouteffect.md":"tzcWKQCn","blogs_react_reacthooks_usememo.md":"heOeHkbi","blogs_react_reacthooks_usereducer.md":"B5BJinyF","blogs_react_reacthooks_useref.md":"BEkoC6JJ","blogs_react_reacthooks_usestate.md":"RxbaxTL1","blogs_vue_diff.md":"p9XNT1zb","blogs_vue_directives.md":"DeDHLIdm","blogs_vue_draggbletable.md":"DAuG4LxW","blogs_vue_permission.md":"DHoel9CO","blogs_vue_vue3.md":"CXqOJ3Hq","blogs_vue_vue3scale.md":"9TFoyqcG","blogs_vue_vue3tinymce.md":"BzFY9VOL","blogs_web_css_funny_css.md":"DmvZP35y","blogs_web_css_timeline.md":"BNss2Glc","blogs_web_faceauth.md":"BAzyHYG7","blogs_web_h5issue.md":"kNXinVXT","blogs_web_mini_canvas_signture.md":"DkJOhBk_","blogs_web_mini_mini_dev.md":"DMiU0KbM","blogs_web_mini_readme.md":"GRkItIy8","blogs_web_seo.md":"CxDlfyWP","blogs_web_weboptimize.md":"CYyBHsz2","docs_about_readme.md":"OoHbh_D_","docs_mallcook_readme.md":"CDD8gLvd","docs_yft_readme.md":"BnlT6Gvs","index.md":"B6svR78F","other_about.md":"HisTBvZc","other_androidkeystore.md":"9Ros05Sz","other_bat.md":"DAPSrhmt","other_charles.md":"DdSC2xaO","other_fixbuginwork.md":"Bxm2uu9e","other_homebrew.md":"DOzPmWf3","other_nginx.md":"DcHdzvOv","other_npm.md":"DD4TZhiZ","other_parcel.md":"BGJQhrYX","other_pnpm.md":"d4hr0jx1","other_typescrpt.md":"jPMzJsIx","other_winplanwork.md":"CLyHTSoz","products_github.md":"CoUP-FJS","products_works.md":"CV0yYDau"}
